sbump.py
sbump-0.1.1.dist-info/METADATA
sbump-0.1.1.dist-info/WHEEL
sbump-0.1.1.dist-info/entry_points.txt
sbump-0.1.1.dist-info/RECORD
