Metadata-Version: 2.3
Name: sbump
Version: 0.1.1
Summary: SimpleBump, bump a static project.version in pyproject.toml, no config, no hassle
Requires-Python: >=3.11
Requires-Dist: click>=8.1.7
Requires-Dist: semver>=3.0.2
Requires-Dist: tomlkit>=0.13.2
